e2e-tests/__init__.py
e2e-tests/test_expense.py
e2e-tests/test_group.py
splitwise/__init__.py
splitwise/__version__.py
splitwise/balance.py
splitwise/category.py
splitwise/comment.py
splitwise/currency.py
splitwise/debt.py
splitwise/error.py
splitwise/exception.py
splitwise/expense.py
splitwise/group.py
splitwise/notification.py
splitwise/picture.py
splitwise/receipt.py
splitwise/user.py
tests/__init__.py
tests/test_addUserToGroup.py
tests/test_createComment.py
tests/test_createExpense.py
tests/test_createGroup.py
tests/test_deleteExpense.py
tests/test_deleteGroup.py
tests/test_getCategories.py
tests/test_getComments.py
tests/test_getCurrencies.py
tests/test_getCurrentUser.py
tests/test_getExpense.py
tests/test_getExpenses.py
tests/test_getFriends.py
tests/test_getGroup.py
tests/test_getGroups.py
tests/test_getNotifications.py
tests/test_getUser.py
tests/test_updateExpense.py
tests/test_updateUser.py
splitwise-3.0.0.dist-info/LICENSE
splitwise-3.0.0.dist-info/METADATA
splitwise-3.0.0.dist-info/WHEEL
splitwise-3.0.0.dist-info/top_level.txt
splitwise-3.0.0.dist-info/RECORD
