Metadata-Version: 2.1
Name: splitwise
Version: 3.0.0
Summary: Splitwise Python SDK
Home-page: https://github.com/namaggarwal/splitwise
Download-URL: https://github.com/namaggarwal/splitwise/tarball/v3.0.0
Author: Naman Aggarwal
Author-email: aggarwal.nam@gmail.com
License: MIT
Project-URL: Documentation, https://splitwise.readthedocs.io
Project-URL: Source, https://github.com/namaggarwal/splitwise
Classifier: Intended Audience :: Developers
Classifier: Natural Language :: English
Classifier: Operating System :: OS Independent
Classifier: Programming Language :: Python
Classifier: Programming Language :: Python :: 3
Classifier: Programming Language :: Python :: 3.7
Classifier: Programming Language :: Python :: 3.8
Classifier: Programming Language :: Python :: 3.9
Classifier: Programming Language :: Python :: 3.10
Classifier: Programming Language :: Python :: 3.11
Classifier: Topic :: Software Development :: Libraries :: Python Modules
License-File: LICENSE
